scrapingbee/__init__.py
scrapingbee/__version__.py
scrapingbee/client.py
scrapingbee/utils.py
scrapingbee-2.0.2.dist-info/METADATA
scrapingbee-2.0.2.dist-info/WHEEL
scrapingbee-2.0.2.dist-info/top_level.txt
scrapingbee-2.0.2.dist-info/RECORD
