Metadata-Version: 2.1
Name: scrapingbee
Version: 2.0.2
Summary: ScrapingBee Python SDK
Home-page: https://github.com/scrapingbee/scrapingbee-python
Author: Ari Bajo Rouvinen
Author-email: arimbr@gmail.com
Maintainer: Pierre de Wulf
Maintainer-email: hello@scrapingbee.com
License: MIT
Classifier: License :: OSI Approved :: MIT License
Classifier: Programming Language :: Python
Classifier: Programming Language :: Python :: 3
Classifier: Programming Language :: Python :: 3.7
Classifier: Programming Language :: Python :: 3.8
Classifier: Programming Language :: Python :: 3.9
Classifier: Programming Language :: Python :: 3.10
Classifier: Programming Language :: Python :: 3.11
Classifier: Topic :: Software Development :: Libraries :: Python Modules
Requires-Python: >=3.8
Requires-Dist: requests
